bs_processors/__init__.py
bs_processors/generic_processors.py
bs_processors/modify.py
bs_processors/predicate.py
bs_processors/processor_util.py
bs_processors/xml_util.py
bs_processors/cli/__init__.py
bs_processors/cli/main.py
bs_processors/utils/__init__.py
bs_processors/utils/compare_xml.py
bs_processors/utils/file_util.py
bs_processors/utils/util.py
bs_processors/utils/pytest/__init__.py
bs_processors/utils/pytest/fixtures.py
bs_processors-0.0.1rc10.dist-info/LICENSE
bs_processors-0.0.1rc10.dist-info/METADATA
bs_processors-0.0.1rc10.dist-info/WHEEL
bs_processors-0.0.1rc10.dist-info/entry_points.txt
bs_processors-0.0.1rc10.dist-info/top_level.txt
bs_processors-0.0.1rc10.dist-info/RECORD
